Workbook

Sheet Sheet1
A1: 线上订单号 | B1: 品牌 | C1: 店铺 | D1: 订单日期 | E1: 商品名称 | F1: 工厂 | G1: 商品工厂 | H1: 商品编码 | I1: 成本价 | J1: 标费运费 | K1: 平台扣点 | L1: 总成本 | M1: 销售数量 | N1: 销售金额 | O1: 销售毛利 | P1: 销售毛利率
A2: 5122610136099021717 | B2: 初医生 | C2: 淘宝天猫-初医生旗舰店 | D2: 46205 | E2: 长颈鹿抱枕内衬款 | F2: 佳雷 | G2: 佳雷-长颈鹿抱枕内衬款 | H2: CYS-JLBZCJLPWC01001 | I2: =VLOOKUP(H2,[1]物料!$A$1:$M$65536,13,0) -> 43.30 | J2: 3.5 | K2: =N2*0.05 -> 4.896 | L2: =I2+J2+K2 -> 51.696 | M2: 1 | N2: 97.92 | O2: =N2-L2 -> 46.224 | P2: =O2/N2 -> 0.47205882
A3: 5122574748819055816 | B3: 猫人 | C3: 淘宝天猫-猫人严选旗舰店 | D3: 46205 | E3: 冥想坐垫 | F3: 佳雷 | G3: 佳雷-冥想坐垫 | H3: JLZDMXKJC01001 | I3: =VLOOKUP(H3,[1]物料!$A$1:$M$65536,13,0) -> 115.60 | J3: 13.5 | K3: =N3*0.05 -> 12.139 | L3: =I3+J3+K3 -> 141.239 | M3: 1 | N3: 242.78 | O3: =N3-L3 -> 101.541 | P3: =O3/N3 -> 0.41824285
A4: 5122574748819055816 | B4: 猫人 | C4: 淘宝天猫-猫人严选旗舰店 | D4: 46205 | E4: 冥想坐垫 | F4: 佳雷 | G4: 佳雷-冥想坐垫 | H4: JLZDMXKJC01002 | I4: =VLOOKUP(H4,[1]物料!$A$1:$M$65536,13,0) -> 115.60 | J4: 13.5 | K4: =N4*0.05 -> 12.139 | L4: =I4+J4+K4 -> 141.239 | M4: 1 | N4: 242.78 | O4: =N4-L4 -> 101.541 | P4: =O4/N4 -> 0.41824285
A5: 3311087737167074172 | B5: 初医生 | C5: 淘宝天猫-初医生旗舰店 | D5: 46205 | E5: 小袋鼠儿童抱枕中号 | F5: 华雷 | G5: 华雷-小袋鼠儿童抱枕中号 | H5: CYS-XDSETBZBS02 | I5: =VLOOKUP(H5,[1]物料!$A$1:$M$65536,13,0) -> 43.00 | J5: 13.6 | K5: =N5*0.05 -> 5.9755 | L5: =I5+J5+K5 -> 62.5755 | M5: 1 | N5: 119.51 | O5: =N5-L5 -> 56.9345 | P5: =O5/N5 -> 0.47639946
A6: 3311087737167074172 | B6: 初医生 | C6: 淘宝天猫-初医生旗舰店 | D6: 46205 | E6: 小袋鼠儿童抱枕中号 | F6: 华雷 | G6: 华雷-小袋鼠儿童抱枕中号 | H6: CYS-XDSETBZFS05 | I6: =VLOOKUP(H6,[1]物料!$A$1:$M$65536,13,0) -> 43.00 | J6: 13.6 | K6: =N6*0.05 -> 5.9755 | L6: =I6+J6+K6 -> 62.5755 | M6: 1 | N6: 119.51 | O6: =N6-L6 -> 56.9345 | P6: =O6/N6 -> 0.47639946
A7: 5122687897862017910 | B7: 猫人 | C7: 淘宝天猫-猫人严选旗舰店 | D7: 46205 | E7: 冥想坐垫 | F7: 佳雷 | G7: 佳雷-冥想坐垫 | H7: JLZDMXKJC01001 | I7: =VLOOKUP(H7,[1]物料!$A$1:$M$65536,13,0) -> 115.60 | J7: 13.5 | K7: =N7*0.05 -> 12.139 | L7: =I7+J7+K7 -> 141.239 | M7: 1 | N7: 242.78 | O7: =N7-L7 -> 101.541 | P7: =O7/N7 -> 0.41824285
A8: 5122687897862017910 | B8: 猫人 | C8: 淘宝天猫-猫人严选旗舰店 | D8: 46205 | E8: 冥想坐垫 | F8: 佳雷 | G8: 佳雷-冥想坐垫 | H8: JLZDMXKJC01001 | I8: =VLOOKUP(H8,[1]物料!$A$1:$M$65536,13,0) -> 115.60 | J8: 13.5 | K8: =N8*0.05 -> 12.139 | L8: =I8+J8+K8 -> 141.239 | M8: 1 | N8: 242.78 | O8: =N8-L8 -> 101.541 | P8: =O8/N8 -> 0.41824285
A9: 5122687897862017910 | B9: 猫人 | C9: 淘宝天猫-猫人严选旗舰店 | D9: 46205 | E9: 冥想坐垫 | F9: 佳雷 | G9: 佳雷-冥想坐垫 | H9: JLZDMXKJC01001 | I9: =VLOOKUP(H9,[1]物料!$A$1:$M$65536,13,0) -> 115.60 | J9: 13.5 | K9: =N9*0.05 -> 12.139 | L9: =I9+J9+K9 -> 141.239 | M9: 1 | N9: 242.78 | O9: =N9-L9 -> 101.541 | P9: =O9/N9 -> 0.41824285
A10: 5122691605699092108,18266689:5122189155360000907,18266689:5122691605699092108 | B10: 猫人 | C10: 淘宝天猫-猫人严选旗舰店 | D10: 46205 | E10: 芭蕾舞鞋 | F10: 善艺 | G10: 善艺-芭蕾舞鞋 | H10: 芭蕾舞山茶花（白色39-40） | I10: =VLOOKUP(H10,[1]物料!$A$1:$M$65536,13,0) -> 19.00 | J10: 5.4 | K10: =N10*0.05 -> 1.845 | L10: =I10+J10+K10 -> 26.245 | M10: 1 | N10: 36.9 | O10: =N10-L10 -> 10.655 | P10: =O10/N10 -> 0.28875339
A11: 5122691605699092108,18266689:5122189155360000907,18266689:5122691605699092108 | B11: 猫人 | C11: 淘宝天猫-猫人严选旗舰店 | D11: 46205 | E11: 芭蕾舞鞋 | F11: 善艺 | G11: 善艺-芭蕾舞鞋 | H11: 芭蕾舞山茶花（黑色37-38） | I11: =VLOOKUP(H11,[1]物料!$A$1:$M$65536,13,0) -> 19.00 | J11: 5.4 | K11: =N11*0.05 -> 1.845 | L11: =I11+J11+K11 -> 26.245 | M11: 1 | N11: 36.9 | O11: =N11-L11 -> 10.655 | P11: =O11/N11 -> 0.28875339
A12: 260702-641749491250113 | B12: 猫人 | C12: 拼多多-猫人布艺旗舰店 | D12: 46205 | E12: 四叶草褥疮坐垫凝胶卫衣布款 | F12: 佳雷 | G12: 佳雷-四叶草褥疮坐垫凝胶卫衣布款 | H12: JLZDRCNJWYBC01001 | I12: =VLOOKUP(H12,[1]物料!$A$1:$M$65536,13,0) -> 36.10 | J12: 6.5 | K12: =N12*0.05 -> 4.435 | L12: =I12+J12+K12 -> 47.035 | M12: 1 | N12: 88.7 | O12: =N12-L12 -> 41.665 | P12: =O12/N12 -> 0.46972943
A13: 260702-020059287052263 | B13: 初医生 | C13: 拼多多-初医生家纺官方旗舰店 | D13: 46205 | E13: 双层午睡枕 | F13: 佳雷 | G13: 佳雷-双层午睡枕 | H13: CYS-JLWSSCPWP01004 | I13: =VLOOKUP(H13,[1]物料!$A$1:$M$65536,13,0) -> 21.00 | J13: 3 | K13: =N13*0.05 -> 2.495 | L13: =I13+J13+K13 -> 26.495 | M13: 1 | N13: 49.9 | O13: =N13-L13 -> 23.405 | P13: =O13/N13 -> 0.46903808
... A509: 5122183539361098821 | B509: 初医生 | C509: 淘宝天猫-初医生旗舰店 | D509: 46205 | E509: 长颈鹿抱枕内衬款 | F509: 佳雷 | G509: 佳雷-长颈鹿抱枕内衬款 | H509: CYS-JLBZCJLPWC01003 | I509: =VLOOKUP(H509,[1]物料!$A$1:$M$65536,13,0) -> 43.30 | J509: 3.5 | K509: =N509*0.05 -> 4.651 | L509: =I509+J509+K509 -> 51.451 | M509: 1 | N509: 93.02 | O509: =N509-L509 -> 41.569 | P509: =O509/N509 -> 0.44688239
A510: 260702-062096720263728 | B510: 猫人 | C510: 拼多多-猫人家具家纺旗舰店 | D510: 46205 | E510: 海马长条抱枕特大号 | F510: 眠语 | G510: 眠语-海马长条抱枕特大号 | H510: HMCTBZTDHDLS04 | I510: 52 | J510: 18 | K510: =N510*0.05 -> 7.04 | L510: =I510+J510+K510 -> 77.04 | M510: 1 | N510: 140.8 | O510: =N510-L510 -> 63.76 | P510: =O510/N510 -> 0.45284091
A511: 260702-623378481542326 | B511: 猫人 | C511: 拼多多-猫人布艺旗舰店 | D511: 46205 | E511: 锦氨男朋友枕 | F511: 永光 | G511: 永光-锦氨男朋友枕 | H511: 锦氨男朋友枕深灰色150 | I511: =VLOOKUP(H511,[1]物料!$A$1:$M$65536,13,0) -> 42.00 | J511: 8 | K511: =N511*0.05 -> 5.94 | L511: =I511+J511+K511 -> 55.94 | M511: 1 | N511: 118.8 | O511: =N511-L511 -> 62.86 | P511: =O511/N511 -> 0.52912458
A512: 260702-404540659321947 | B512: 猫人 | C512: 拼多多-猫人布艺旗舰店 | D512: 46205 | E512: 男朋友枕 | F512: 永光 | G512: 永光-男朋友枕 | H512: 男朋友枕凉感蓝 | I512: =VLOOKUP(H512,[1]物料!$A$1:$M$65536,13,0) -> 24.00 | J512: 8 | K512: =N512*0.05 -> 3.26 | L512: =I512+J512+K512 -> 35.26 | M512: 1 | N512: 65.2 | O512: =N512-L512 -> 29.94 | P512: =O512/N512 -> 0.45920245
A513: 260702-164353820223591 | B513: 初医生 | C513: 拼多多-初医生家纺官方旗舰店 | D513: 46205 | E513: 云环坐垫 | F513: 眠语 | G513: 眠语-云环坐垫 | H513: CYS-YHZDHHS | I513: =VLOOKUP(H513,[1]物料!$A$1:$M$65536,13,0) -> 20.00 | J513: 4.5 | K513: =N513*0.05 -> 2.99 | L513: =I513+J513+K513 -> 27.49 | M513: 1 | N513: 59.8 | O513: =N513-L513 -> 32.31 | P513: =O513/N513 -> 0.540301
A514: 260702-496794344960404 | B514: 猫人 | C514: 拼多多-猫人生活家具旗舰店 | D514: 46205 | E514: 圆点趴趴枕 | F514: 禹鹏 | G514: 禹鹏-圆点趴趴枕 | H514: YDPPZ-PH | I514: =VLOOKUP(H514,[1]物料!$A$1:$M$65536,13,0) -> 45.00 | J514: 6.5 | K514: =N514*0.05 -> 5.75 | L514: =I514+J514+K514 -> 57.25 | M514: 1 | N514: 115 | O514: =N514-L514 -> 57.75 | P514: =O514/N514 -> 0.50217391
A515: 5122182531993023727 | B515: 猫人 | C515: 淘宝天猫-猫人严选旗舰店 | D515: 46205 | E515: 趴趴枕套装 | F515: 禹鹏 | G515: 禹鹏-趴趴枕套装 | H515: FJL-PPZ-QH | I515: =VLOOKUP(H515,[1]物料!$A$1:$M$65536,13,0) -> 42.00 | J515: 6.5 | K515: =N515*0.05 -> 5.49 | L515: =I515+J515+K515 -> 53.99 | M515: 1 | N515: 109.8 | O515: =N515-L515 -> 55.81 | P515: =O515/N515 -> 0.5082878
A516: 260702-370000535052074 | B516: 猫人 | C516: 拼多多-猫人家具家纺旗舰店 | D516: 46205 | E516: 锦氨男朋友枕 | F516: 永光 | G516: 永光-锦氨男朋友枕 | H516: 锦氨男朋友枕蓝色 | I516: =VLOOKUP(H516,[1]物料!$A$1:$M$65536,13,0) -> 25.00 | J516: 8 | K516: =N516*0.05 -> 3.265 | L516: =I516+J516+K516 -> 36.265 | M516: 1 | N516: 65.3 | O516: =N516-L516 -> 29.035 | P516: =O516/N516 -> 0.44464012
A517: 5122184907105009642 | B517: 初医生 | C517: 淘宝天猫-初医生旗舰店 | D517: 46205 | E517: 男朋友枕 | F517: 永光 | G517: 永光-男朋友枕 | H517: 男朋友枕凉感蓝 | I517: =VLOOKUP(H517,[1]物料!$A$1:$M$65536,13,0) -> 24.00 | J517: 4.5 | K517: =N517*0.05 -> 3.3155 | L517: =I517+J517+K517 -> 31.8155 | M517: 1 | N517: 66.31 | O517: =N517-L517 -> 34.4945 | P517: =O517/N517 -> 0.52020057
A518: 3311269428860154383 | B518: 猫人 | C518: 淘宝天猫-猫人居家布艺旗舰 | D518: 46205 | E518: 8字坐垫 | F518: 佳雷 | G518: 佳雷-8字坐垫 | H518: JLZDBZPWP01003 | I518: =VLOOKUP(H518,[1]物料!$A$1:$M$65536,13,0) -> 19.90 | J518: 6.5 | K518: =N518*0.05 -> 2.99 | L518: =I518+J518+K518 -> 29.39 | M518: 1 | N518: 59.8 | O518: =N518-L518 -> 30.41 | P518: =O518/N518 -> 0.50852843
A519: 3311084281496036176 | B519: 初医生 | C519: 淘宝天猫-初医生旗舰店 | D519: 46205 | E519: 防侧睡护理枕 | F519: 佳雷 | G519: 佳雷-防侧睡护理枕 | H519: CYS-JLZTFCPWP01002 | I519: =VLOOKUP(H519,[1]物料!$A$1:$M$65536,13,0) -> 21.10 | J519: 3 | K519: =N519*0.05 -> 2.691 | L519: =I519+J519+K519 -> 26.791 | M519: 1 | N519: 53.82 | O519: =N519-L519 -> 27.029 | P519: =O519/N519 -> 0.50221107
A520: 260702-255684831541700 | B520: 猫人 | C520: 拼多多-猫人智能家居旗舰店 | D520: 46205 | E520: 防侧睡护理枕 | F520: 佳雷 | G520: 佳雷-防侧睡护理枕 | H520: JLZTFCPWP01001 | I520: =VLOOKUP(H520,[1]物料!$A$1:$M$65536,13,0) -> 21.10 | J520: 6.5 | K520: =N520*0.05 -> 2.98 | L520: =I520+J520+K520 -> 30.58 | M520: 1 | N520: 59.6 | O520: =N520-L520 -> 29.02 | P520: =O520/N520 -> 0.48691275
A521: 5122374230048032715 | B521: 初医生 | C521: 淘宝天猫-初医生旗舰店 | D521: 46205 | E521: 四叶草褥疮坐垫凝胶小菱格款 | F521: 佳雷 | G521: 佳雷-四叶草褥疮坐垫凝胶小菱格款 | H521: CYS-JLZDRCNJLGC01001 | I521: =VLOOKUP(H521,[1]物料!$A$1:$M$65536,13,0) -> 36.60 | J521: 3 | K521: =N521*0.05 -> 4.883 | L521: =I521+J521+K521 -> 44.483 | M521: 1 | N521: 97.66 | O521: =N521-L521 -> 53.177 | P521: =O521/N521 -> 0.54451157
A522: 3547462001622962 | B522: 初医生 | C522: 京东-DR.CHU 初医生官方旗舰店 | D522: 46205 | E522: 长颈鹿抱枕内衬款 | F522: 佳雷 | G522: 佳雷-长颈鹿抱枕内衬款 | H522: CYS-JLBZCJLPWC01002 | I522: =VLOOKUP(H522,[1]物料!$A$1:$M$65536,13,0) -> 43.30 | J522: 3.5 | K522: =N522*0.05 -> 5.44 | L522: =I522+J522+K522 -> 52.24 | M522: 1 | N522: 108.8 | O522: =N522-L522 -> 56.56 | P522: =O522/N522 -> 0.51985294
... A2363: 260702-063973650020635 | B2363: 猫人 | C2363: 拼多多-猫人智能家居旗舰店 | D2363: 46205 | E2363: 男朋友枕 | F2363: 永光 | G2363: 永光-男朋友枕 | H2363: 男朋友枕凉感蓝 | I2363: =VLOOKUP(H2363,[1]物料!$A$1:$M$65536,13,0) -> 24.00 | J2363: 8 | K2363: =N2363*0.05 -> 3.225 | L2363: =I2363+J2363+K2363 -> 35.225 | M2363: 1 | N2363: 64.5 | O2363: =N2363-L2363 -> 29.275 | P2363: =O2363/N2363 -> 0.45387597
A2364: 260702-224751787622168 | B2364: 猫人 | C2364: 拼多多-猫人家具家纺旗舰店 | D2364: 46205 | E2364: 海豚抱枕 | F2364: 眠语 | G2364: 眠语-海豚抱枕 | H2364: HTBZHS02 | I2364: 65 | J2364: 10.7 | K2364: =N2364*0.05 -> 8.55 | L2364: =I2364+J2364+K2364 -> 84.25 | M2364: 1 | N2364: 171 | O2364: =N2364-L2364 -> 86.75 | P2364: =O2364/N2364 -> 0.50730994
A2365: 5122058295494251444 | B2365: 初医生 | C2365: 淘宝天猫-初医生旗舰店 | D2365: 46205 | E2365: 海马长条抱枕小号 | F2365: 眠语 | G2365: 眠语-海马长条抱枕小号 | H2365: CYS-HMCTBZXHZS05 | I2365: =VLOOKUP(H2365,[1]物料!$A$1:$M$65536,13,0) -> 40.00 | J2365: 7.2 | K2365: =N2365*0.05 -> 4.6125 | L2365: =I2365+J2365+K2365 -> 51.8125 | M2365: 1 | N2365: 92.25 | O2365: =N2365-L2365 -> 40.4375 | P2365: =O2365/N2365 -> 0.43834688
A2366: 5122059555886018336 | B2366: 初医生 | C2366: 淘宝天猫-初医生旗舰店 | D2366: 46205 | E2366: 海马长条抱枕大号 | F2366: 眠语 | G2366: 眠语-海马长条抱枕大号 | H2366: CYS-HMCTBZDHHS | I2366: =VLOOKUP(H2366,[1]物料!$A$1:$M$65536,13,0) -> 40.00 | J2366: 7.2 | K2366: =N2366*0.05 -> 6.9345 | L2366: =I2366+J2366+K2366 -> 54.1345 | M2366: 1 | N2366: 138.69 | O2366: =N2366-L2366 -> 84.5555 | P2366: =O2366/N2366 -> 0.60967265
A2367: 5122566181653002525 | B2367: 初医生 | C2367: 淘宝天猫-初医生旗舰店 | D2367: 46205 | E2367: 海马长条抱枕大号 | F2367: 眠语 | G2367: 眠语-海马长条抱枕大号 | H2367: CYS-HMCTBZDHHS | I2367: =VLOOKUP(H2367,[1]物料!$A$1:$M$65536,13,0) -> 40.00 | J2367: 7.2 | K2367: =N2367*0.05 -> 6.9345 | L2367: =I2367+J2367+K2367 -> 54.1345 | M2367: 1 | N2367: 138.69 | O2367: =N2367-L2367 -> 84.5555 | P2367: =O2367/N2367 -> 0.60967265
A2368: 260702-431489042050532 | B2368: 猫人 | C2368: 拼多多-猫人布艺旗舰店 | D2368: 46205 | E2368: 拼色多功能趴睡带头枕 | F2368: 眠语 | G2368: 眠语-拼色多功能趴睡带头枕 | H2368: PSDGNPSZDTHBS10 | I2368: =VLOOKUP(H2368,[1]物料!$A$1:$M$65536,13,0) -> 48.00 | J2368: 10.7 | K2368: =N2368*0.05 -> 6.44 | L2368: =I2368+J2368+K2368 -> 65.14 | M2368: 1 | N2368: 128.8 | O2368: =N2368-L2368 -> 63.66 | P2368: =O2368/N2368 -> 0.49425466
A2369: 3310545974235018599 | B2369: 猫人 | C2369: 淘宝天猫-猫人居家布艺旗舰 | D2369: 46205 | E2369: 男朋友枕 | F2369: 永光 | G2369: 永光-男朋友枕 | H2369: 男朋友枕凉感粉 | I2369: =VLOOKUP(H2369,[1]物料!$A$1:$M$65536,13,0) -> 24.00 | J2369: 8 | K2369: =N2369*0.05 -> 3.49 | L2369: =I2369+J2369+K2369 -> 35.49 | M2369: 1 | N2369: 69.8 | O2369: =N2369-L2369 -> 34.31 | P2369: =O2369/N2369 -> 0.49154728
A2370: 3310542734899036876 | B2370: 初医生 | C2370: 淘宝天猫-初医生旗舰店 | D2370: 46205 | E2370: 响尾蛇 | F2370: 善艺 | G2370: 善艺-响尾蛇 | H2370: 响尾蛇【黑色38-39】 | I2370: =VLOOKUP(H2370,[1]物料!$A$1:$M$65536,13,0) -> 23.90 | J2370: 1.9 | K2370: =N2370*0.05 -> 2.24 | L2370: =I2370+J2370+K2370 -> 28.04 | M2370: 1 | N2370: 44.8 | O2370: =N2370-L2370 -> 16.76 | P2370: =O2370/N2370 -> 0.37410714
A2371: 260702-259690350102781 | B2371: 猫人 | C2371: 拼多多-MiiOW猫人户外用品旗舰店 | D2371: 46205 | E2371: 随行家居拖 | F2371: 佐肯 | G2371: 佐肯-随行家居拖 | H2371: 90426746663B0815 | I2371: =VLOOKUP(H2371,[1]物料!$A$1:$M$65536,13,0) -> 8.00 | J2371: 6.3 | K2371: =N2371*0.05 -> 1.05 | L2371: =I2371+J2371+K2371 -> 15.35 | M2371: 1 | N2371: 21 | O2371: =N2371-L2371 -> 5.65 | P2371: =O2371/N2371 -> 0.26904762
A2372: 260702-431489041942781 | B2372: 猫人 | C2372: 拼多多-MiiOW猫人户外用品旗舰店 | D2372: 46205 | E2372: 随行家居拖 | F2372: 佐肯 | G2372: 佐肯-随行家居拖 | H2372: 9042674666311213 | I2372: =VLOOKUP(H2372,[1]物料!$A$1:$M$65536,13,0) -> 8.00 | J2372: 6.3 | K2372: =N2372*0.05 -> 1.05 | L2372: =I2372+J2372+K2372 -> 15.35 | M2372: 1 | N2372: 21 | O2372: =N2372-L2372 -> 5.65 | P2372: =O2372/N2372 -> 0.26904762
A2373: 260702-087891658262781 | B2373: 猫人 | C2373: 拼多多-MiiOW猫人户外用品旗舰店 | D2373: 46205 | E2373: 随行家居拖 | F2373: 佐肯 | G2373: 佐肯-随行家居拖 | H2373: 9042674666371614 | I2373: =VLOOKUP(H2373,[1]物料!$A$1:$M$65536,13,0) -> 8.00 | J2373: 6.3 | K2373: =N2373*0.05 -> 1.05 | L2373: =I2373+J2373+K2373 -> 15.35 | M2373: 1 | N2373: 21 | O2373: =N2373-L2373 -> 5.65 | P2373: =O2373/N2373 -> 0.26904762
A2374: 260702-549432922512799 | B2374: 猫人 | C2374: 拼多多-猫人智能家居旗舰店 | D2374: 46205 | E2374: 男朋友枕 | F2374: 永光 | G2374: 永光-男朋友枕 | H2374: 男朋友枕凉感蓝 | I2374: =VLOOKUP(H2374,[1]物料!$A$1:$M$65536,13,0) -> 24.00 | J2374: 8 | K2374: =N2374*0.05 -> 3.435 | L2374: =I2374+J2374+K2374 -> 35.435 | M2374: 1 | N2374: 68.7 | O2374: =N2374-L2374 -> 33.265 | P2374: =O2374/N2374 -> 0.4842067
A2375: 260702-603287775661352 | B2375: 猫人 | C2375: 拼多多-猫人智能家居旗舰店 | D2375: 46205 | E2375: 男朋友枕 | F2375: 永光 | G2375: 永光-男朋友枕 | H2375: 男朋友枕凉感蓝 | I2375: =VLOOKUP(H2375,[1]物料!$A$1:$M$65536,13,0) -> 24.00 | J2375: 8 | K2375: =N2375*0.05 -> 3.435 | L2375: =I2375+J2375+K2375 -> 35.435 | M2375: 1 | N2375: 68.7 | O2375: =N2375-L2375 -> 33.265 | P2375: =O2375/N2375 -> 0.4842067
A2376: 260702-129625024853406 | B2376: 猫人 | C2376: 拼多多-猫人生活家具旗舰店 | D2376: 46205 | E2376: 男朋友枕 | F2376: 永光 | G2376: 永光-男朋友枕 | H2376: 男朋友枕凉感蓝 | I2376: =VLOOKUP(H2376,[1]物料!$A$1:$M$65536,13,0) -> 24.00 | J2376: 8 | K2376: =N2376*0.05 -> 3.435 | L2376: =I2376+J2376+K2376 -> 35.435 | M2376: 1 | N2376: 68.7 | O2376: =N2376-L2376 -> 33.265 | P2376: =O2376/N2376 -> 0.4842067
... A9456: 260628-013946068612299 | B9456: 猫人 | C9456: 拼多多-猫人家纺家居旗舰店 | D9456: 46201 | E9456: 海马长条抱枕特大号 | F9456: 眠语 | G9456: 眠语-海马长条抱枕特大号 | H9456: HMCTBZTDHLS02 | I9456: =VLOOKUP(H9456,[1]物料!$A$1:$M$65536,13,0) -> 52.00 | J9456: 18 | K9456: =N9456*0.05 -> 6.9315 | L9456: =I9456+J9456+K9456 -> 76.9315 | M9456: 1 | N9456: 138.63 | O9456: =N9456-L9456 -> 61.6985 | P9456: =O9456/N9456 -> 0.44505879
A9457: 260628-569922077002381 | B9457: 猫人 | C9457: 拼多多-猫人智能家居旗舰店 | D9457: 46201 | E9457: 海豚抱枕 | F9457: 眠语 | G9457: 眠语-海豚抱枕 | H9457: HTBZHS02 | I9457: 65 | J9457: 10.7 | K9457: =N9457*0.05 -> 8.229 | L9457: =I9457+J9457+K9457 -> 83.929 | M9457: 1 | N9457: 164.58 | O9457: =N9457-L9457 -> 80.651 | P9457: =O9457/N9457 -> 0.49004132
A9458: 3310645297398217291 | B9458: 猫人 | C9458: 淘宝天猫-猫人居家布艺旗舰 | D9458: 46201 | E9458: 新款痔疮坐垫 | F9458: 佳雷 | G9458: 佳雷-新款痔疮坐垫 | H9458: JLZDZC3MC01001 | I9458: =VLOOKUP(H9458,[1]物料!$A$1:$M$65536,13,0) -> 22.10 | J9458: 6.5 | K9458: =N9458*0.05 -> 3.34 | L9458: =I9458+J9458+K9458 -> 31.94 | M9458: 1 | N9458: 66.8 | O9458: =N9458-L9458 -> 34.86 | P9458: =O9458/N9458 -> 0.52185629
A9459: 5121709923368002208 | B9459: 初医生 | C9459: 淘宝天猫-初医生旗舰店 | D9459: 46201 | E9459: 海马长条抱枕大号 | F9459: 眠语 | G9459: 眠语-海马长条抱枕大号 | H9459: CYS-HMCTBZDHHS | I9459: =VLOOKUP(H9459,[1]物料!$A$1:$M$65536,13,0) -> 40.00 | J9459: 7.2 | K9459: =N9459*0.05 -> 6.588 | L9459: =I9459+J9459+K9459 -> 53.788 | M9459: 1 | N9459: 131.76 | O9459: =N9459-L9459 -> 77.972 | P9459: =O9459/N9459 -> 0.59177292
A9460: 260628-638771577132794 | B9460: 初医生 | C9460: 拼多多-初医生家纺官方旗舰店 | D9460: 46201 | E9460: 双层午睡枕 | F9460: 佳雷 | G9460: 佳雷-双层午睡枕 | H9460: CYS-JLWSSCPWP01003 | I9460: =VLOOKUP(H9460,[1]物料!$A$1:$M$65536,13,0) -> 21.00 | J9460: 3 | K9460: =N9460*0.05 -> 2.495 | L9460: =I9460+J9460+K9460 -> 26.495 | M9460: 1 | N9460: 49.9 | O9460: =N9460-L9460 -> 23.405 | P9460: =O9460/N9460 -> 0.46903808
A9461: 260628-525378599201093 | B9461: 初医生 | C9461: 拼多多-初医生家居旗舰店 | D9461: 46201 | E9461: 响尾蛇 | F9461: 善艺 | G9461: 善艺-响尾蛇 | H9461: 响尾蛇【树莓粉38-39】 | I9461: =VLOOKUP(H9461,[1]物料!$A$1:$M$65536,13,0) -> 23.90 | J9461: 1.9 | K9461: =N9461*0.05 -> 2.6 | L9461: =I9461+J9461+K9461 -> 28.4 | M9461: 1 | N9461: 52 | O9461: =N9461-L9461 -> 23.6 | P9461: =O9461/N9461 -> 0.45384615
A9462: 6954060642279233212 | B9462: 猫人 | C9462: 抖音-猫人用品居家布艺专卖店 | D9462: 46201 | E9462: 趴趴枕套装 | F9462: 禹鹏 | G9462: 禹鹏-趴趴枕套装 | H9462: FJL-PPZ-SH | I9462: =VLOOKUP(H9462,[1]物料!$A$1:$M$65536,13,0) -> 42.00 | J9462: 6.5 | K9462: =N9462*0.05 -> 4.94 | L9462: =I9462+J9462+K9462 -> 53.44 | M9462: 1 | N9462: 98.8 | O9462: =N9462-L9462 -> 45.36 | P9462: =O9462/N9462 -> 0.45910931
A9463: 5122135692181046543 | B9463: 初医生 | C9463: 淘宝天猫-初医生旗舰店 | D9463: 46201 | E9463: 四叶草褥疮坐垫凝胶小菱格款 | F9463: 佳雷 | G9463: 佳雷-四叶草褥疮坐垫凝胶小菱格款 | H9463: CYS-JLZDRCNJLGC01001 | I9463: =VLOOKUP(H9463,[1]物料!$A$1:$M$65536,13,0) -> 36.60 | J9463: 3 | K9463: =N9463*0.05 -> 4.693 | L9463: =I9463+J9463+K9463 -> 44.293 | M9463: 1 | N9463: 93.86 | O9463: =N9463-L9463 -> 49.567 | P9463: =O9463/N9463 -> 0.52809504
A9464: 260628-368815674922405 | B9464: 初医生 | C9464: 拼多多-初医生家纺官方旗舰店 | D9464: 46201 | E9464: 狗头腰靠+元抱午睡枕 | F9464: 眠语 | G9464: 眠语-狗头腰靠+元抱午睡枕 | H9464: CYS-GTYKYBWSZGS04 | I9464: =VLOOKUP(H9464,[1]物料!$A$1:$M$65536,13,0) -> 30.00 | J9464: 7.2 | K9464: =N9464*0.05 -> 4.185 | L9464: =I9464+J9464+K9464 -> 41.385 | M9464: 1 | N9464: 83.7 | O9464: =N9464-L9464 -> 42.315 | P9464: =O9464/N9464 -> 0.50555556
A9465: 260628-508936907053273 | B9465: 初医生 | C9465: 拼多多-初医生居家布艺官方旗舰店 | D9465: 46201 | E9465: 半圆痔疮垫 | F9465: 眠语 | G9465: 眠语-半圆痔疮垫 | H9465: CYS-BYZCDSHS | I9465: =VLOOKUP(H9465,[1]物料!$A$1:$M$65536,13,0) -> 20.00 | J9465: 4.5 | K9465: =N9465*0.05 -> 2.745 | L9465: =I9465+J9465+K9465 -> 27.245 | M9465: 1 | N9465: 54.9 | O9465: =N9465-L9465 -> 27.655 | P9465: =O9465/N9465 -> 0.50373406
A9466: 5122214461265022546 | B9466: 初医生 | C9466: 淘宝天猫-初医生旗舰店 | D9466: 46201 | E9466: 响尾蛇 | F9466: 善艺 | G9466: 善艺-响尾蛇 | H9466: 响尾蛇【白色38-39】 | I9466: =VLOOKUP(H9466,[1]物料!$A$1:$M$65536,13,0) -> 23.90 | J9466: 1.9 | K9466: =N9466*0.05 -> 2.24 | L9466: =I9466+J9466+K9466 -> 28.04 | M9466: 1 | N9466: 44.8 | O9466: =N9466-L9466 -> 16.76 | P9466: =O9466/N9466 -> 0.37410714
A9467: 5121907886075040527 | B9467: 猫人 | C9467: 淘宝天猫-猫人严选旗舰店 | D9467: 46201 | E9467: 海马长条抱枕特大号 | F9467: 眠语 | G9467: 眠语-海马长条抱枕特大号 | H9467: HMCTBZTDHLS02 | I9467: =VLOOKUP(H9467,[1]物料!$A$1:$M$65536,13,0) -> 52.00 | J9467: 18 | K9467: =N9467*0.05 -> 7.0665 | L9467: =I9467+J9467+K9467 -> 77.0665 | M9467: 1 | N9467: 141.33 | O9467: =N9467-L9467 -> 64.2635 | P9467: =O9467/N9467 -> 0.4547053
A9468: 3310643893989032069 | B9468: 猫人 | C9468: 淘宝天猫-猫人居家布艺旗舰 | D9468: 46201 | E9468: 透气坐垫 | F9468: 禹鹏 | G9468: 禹鹏-透气坐垫 | H9468: XJL-TQZD-SH | I9468: =VLOOKUP(H9468,[1]物料!$A$1:$M$65536,13,0) -> 20.50 | J9468: 6.5 | K9468: =N9468*0.05 -> 3.94 | L9468: =I9468+J9468+K9468 -> 30.94 | M9468: 1 | N9468: 78.8 | O9468: =N9468-L9468 -> 47.86 | P9468: =O9468/N9468 -> 0.60736041
A9469: 260628-514693599573732 | B9469: 猫人 | C9469: 拼多多-猫人布艺旗舰店 | D9469: 46201 | E9469: 四叶草褥疮坐垫凝胶小菱格款 | F9469: 佳雷 | G9469: 佳雷-四叶草褥疮坐垫凝胶小菱格款 | H9469: JLZDRCNJLGC01001 | I9469: =VLOOKUP(H9469,[1]物料!$A$1:$M$65536,13,0) -> 36.60 | J9469: 6.5 | K9469: =N9469*0.05 -> 4.405 | L9469: =I9469+J9469+K9469 -> 47.505 | M9469: 1 | N9469: 88.1 | O9469: =N9469-L9469 -> 40.595 | P9469: =O9469/N9469 -> 0.4607832
... A11600: 260627-095714035282426 | B11600: 猫人 | C11600: 拼多多-猫人家纺家居旗舰店 | D11600: 46200 | E11600: 海马长条抱枕特大号 | F11600: 眠语 | G11600: 眠语-海马长条抱枕特大号 | H11600: HMCTBZTDHLS02 | I11600: =VLOOKUP(H11600,[1]物料!$A$1:$M$65536,13,0) -> 52.00 | J11600: 18 | K11600: =N11600*0.05 -> 7.04 | L11600: =I11600+J11600+K11600 -> 77.04 | M11600: 1 | N11600: 140.8 | O11600: =N11600-L11600 -> 63.76 | P11600: =O11600/N11600 -> 0.45284091
A11601: 260627-230749642393997 | B11601: 猫人 | C11601: 拼多多-猫人智能家居旗舰店 | D11601: 46200 | E11601: 海豚抱枕 | F11601: 眠语 | G11601: 眠语-海豚抱枕 | H11601: HTBZHS02 | I11601: 65 | J11601: 10.7 | K11601: =N11601*0.05 -> 8.44 | L11601: =I11601+J11601+K11601 -> 84.14 | M11601: 1 | N11601: 168.8 | O11601: =N11601-L11601 -> 84.66 | P11601: =O11601/N11601 -> 0.50154028
A11602: 3310573297184007081 | B11602: 初医生 | C11602: 淘宝天猫-初医生旗舰店 | D11602: 46200 | E11602: 半圆痔疮垫 | F11602: 眠语 | G11602: 眠语-半圆痔疮垫 | H11602: CYS-BYZCDHHS | I11602: =VLOOKUP(H11602,[1]物料!$A$1:$M$65536,13,0) -> 20.00 | J11602: 4.5 | K11602: =N11602*0.05 -> 2.8405 | L11602: =I11602+J11602+K11602 -> 27.3405 | M11602: 1 | N11602: 56.81 | O11602: =N11602-L11602 -> 29.4695 | P11602: =O11602/N11602 -> 0.5187379
A11603: 3310121355773037393 | B11603: 初医生 | C11603: 淘宝天猫-初医生旗舰店 | D11603: 46200 | E11603: 云环坐垫 | F11603: 眠语 | G11603: 眠语-云环坐垫 | H11603: CYS-YHZDZMS | I11603: =VLOOKUP(H11603,[1]物料!$A$1:$M$65536,13,0) -> 20.00 | J11603: 4.5 | K11603: =N11603*0.05 -> 2.983 | L11603: =I11603+J11603+K11603 -> 27.483 | M11603: 1 | N11603: 59.66 | O11603: =N11603-L11603 -> 32.177 | P11603: =O11603/N11603 -> 0.53933959
A11604: 260627-282381597001096 | B11604: 猫人 | C11604: 拼多多-猫人生活家具旗舰店 | D11604: 46200 | E11604: 新款痔疮坐垫 | F11604: 佳雷 | G11604: 佳雷-新款痔疮坐垫 | H11604: JLZDZC3MC01003 | I11604: =VLOOKUP(H11604,[1]物料!$A$1:$M$65536,13,0) -> 22.10 | J11604: 6.5 | K11604: =N11604*0.05 -> 3.34 | L11604: =I11604+J11604+K11604 -> 31.94 | M11604: 1 | N11604: 66.8 | O11604: =N11604-L11604 -> 34.86 | P11604: =O11604/N11604 -> 0.52185629
A11605: 5122135405805044700 | B11605: 初医生 | C11605: 淘宝天猫-初医生旗舰店 | D11605: 46200 | E11605: 云环坐垫 | F11605: 眠语 | G11605: 眠语-云环坐垫 | H11605: CYS-YHZDHHS | I11605: =VLOOKUP(H11605,[1]物料!$A$1:$M$65536,13,0) -> 20.00 | J11605: 4.5 | K11605: =N11605*0.05 -> 2.983 | L11605: =I11605+J11605+K11605 -> 27.483 | M11605: 1 | N11605: 59.66 | O11605: =N11605-L11605 -> 32.177 | P11605: =O11605/N11605 -> 0.53933959
A11606: 5122058184082119332 | B11606: 猫人 | C11606: 淘宝天猫-猫人居家布艺旗舰 | D11606: 46200 | E11606: 海马长条抱枕特大号 | F11606: 眠语 | G11606: 眠语-海马长条抱枕特大号 | H11606: HMCTBZTDHHS01 | I11606: =VLOOKUP(H11606,[1]物料!$A$1:$M$65536,13,0) -> 52.00 | J11606: 18 | K11606: =N11606*0.05 -> 7.44 | L11606: =I11606+J11606+K11606 -> 77.44 | M11606: 1 | N11606: 148.8 | O11606: =N11606-L11606 -> 71.36 | P11606: =O11606/N11606 -> 0.47956989
A11607: 5122134721861071845 | B11607: 初医生 | C11607: 淘宝天猫-初医生旗舰店 | D11607: 46200 | E11607: 长颈鹿抱枕内衬款 | F11607: 佳雷 | G11607: 佳雷-长颈鹿抱枕内衬款 | H11607: CYS-JLBZCJLPWC01005 | I11607: =VLOOKUP(H11607,[1]物料!$A$1:$M$65536,13,0) -> 43.30 | J11607: 3.5 | K11607: =N11607*0.05 -> 4.59 | L11607: =I11607+J11607+K11607 -> 51.39 | M11607: 1 | N11607: 91.8 | O11607: =N11607-L11607 -> 40.41 | P11607: =O11607/N11607 -> 0.44019608
A11608: 3310759596497009250 | B11608: 初医生 | C11608: 淘宝天猫-初医生旗舰店 | D11608: 46200 | E11608: 海马长条抱枕小号 | F11608: 眠语 | G11608: 眠语-海马长条抱枕小号 | H11608: CYS-HMCTBZXHFS | I11608: =VLOOKUP(H11608,[1]物料!$A$1:$M$65536,13,0) -> 40.00 | J11608: 7.2 | K11608: =N11608*0.05 -> 5.1715 | L11608: =I11608+J11608+K11608 -> 52.3715 | M11608: 1 | N11608: 103.43 | O11608: =N11608-L11608 -> 51.0585 | P11608: =O11608/N11608 -> 0.49365271
A11609: 3310148102036004477 | B11609: 猫人 | C11609: 淘宝天猫-猫人居家布艺旗舰 | D11609: 46200 | E11609: 元抱午睡枕 | F11609: 眠语 | G11609: 眠语-元抱午睡枕 | H11609: YBWSZHS04 | I11609: =VLOOKUP(H11609,[1]物料!$A$1:$M$65536,13,0) -> 18.00 | J11609: 8 | K11609: =N11609*0.05 -> 2.94 | L11609: =I11609+J11609+K11609 -> 28.94 | M11609: 1 | N11609: 58.8 | O11609: =N11609-L11609 -> 29.86 | P11609: =O11609/N11609 -> 0.50782313
A11610: 5121828290988037734 | B11610: 猫人 | C11610: 淘宝天猫-猫人严选旗舰店 | D11610: 46200 | E11610: 海马长条抱枕特大号 | F11610: 眠语 | G11610: 眠语-海马长条抱枕特大号 | H11610: HMCTBZTDHLS02 | I11610: =VLOOKUP(H11610,[1]物料!$A$1:$M$65536,13,0) -> 52.00 | J11610: 18 | K11610: =N11610*0.05 -> 7.065 | L11610: =I11610+J11610+K11610 -> 77.065 | M11610: 1 | N11610: 141.3 | O11610: =N11610-L11610 -> 64.235 | P11610: =O11610/N11610 -> 0.45460014
A11611: 260627-134029044141110 | B11611: 猫人 | C11611: 拼多多-猫人家具家纺旗舰店 | D11611: 46200 | E11611: 四叶草褥疮坐垫凝胶小菱格款 | F11611: 佳雷 | G11611: 佳雷-四叶草褥疮坐垫凝胶小菱格款 | H11611: JLZDRCNJLGC01001 | I11611: =VLOOKUP(H11611,[1]物料!$A$1:$M$65536,13,0) -> 36.60 | J11611: 6.5 | K11611: =N11611*0.05 -> 4.095 | L11611: =I11611+J11611+K11611 -> 47.195 | M11611: 1 | N11611: 81.9 | O11611: =N11611-L11611 -> 34.705 | P11611: =O11611/N11611 -> 0.42374847
A11612: 3542466009848639 | B11612: 初医生 | C11612: 京东-DR.CHU 初医生官方旗舰店 | D11612: 46200 | E11612: 萌学护胸午睡枕 | F11612: 眠语 | G11612: 眠语-萌学护胸午睡枕 | H11612: CYS-MXHXWSZFS | I11612: =VLOOKUP(H11612,[1]物料!$A$1:$M$65536,13,0) -> 20.00 | J11612: 4.5 | K11612: =N11612*0.05 -> 2.89 | L11612: =I11612+J11612+K11612 -> 27.39 | M11612: 1 | N11612: 57.8 | O11612: =N11612-L11612 -> 30.41 | P11612: =O11612/N11612 -> 0.52612457
A11613: 3542484014068731 | B11613: 初医生 | C11613: 京东-DR.CHU 初医生官方旗舰店 | D11613: 46200 | E11613: 海马长条抱枕特大号 | F11613: 眠语 | G11613: 眠语-海马长条抱枕特大号 | H11613: CYS-HMCTBZTDHLS02 | I11613: =VLOOKUP(H11613,[1]物料!$A$1:$M$65536,13,0) -> 52.00 | J11613: 14.5 | K11613: =N11613*0.05 -> 6.959 | L11613: =I11613+J11613+K11613 -> 73.459 | M11613: 1 | N11613: 139.18 | O11613: =N11613-L11613 -> 65.721 | P11613: =O11613/N11613 -> 0.47220147
... A14797: 5121542774356052201 | B14797: 猫人 | C14797: 淘宝天猫-猫人严选旗舰店 | D14797: 46199 | E14797: 拼色多功能趴睡带头枕 | F14797: 眠语 | G14797: 眠语-拼色多功能趴睡带头枕 | H14797: PSDGNPSZDTLBS09 | I14797: =VLOOKUP(H14797,[1]物料!$A$1:$M$65536,13,0) -> 48.00 | J14797: 10.7 | K14797: =N14797*0.05 -> 6.5575 | L14797: =I14797+J14797+K14797 -> 65.2575 | M14797: 1 | N14797: 131.15 | O14797: =N14797-L14797 -> 65.8925 | P14797: =O14797/N14797 -> 0.50242089
