Workbook

Sheet Sheet1
A1: 渠道 | B1: 品牌 | C1: 日期 | D1: 工厂 | E1: 商品工厂 | F1: 商品名称 | G1: 商品编码 | H1: 成本价 | I1: 标费运费 | J1: 平台扣点 | K1: 总成本 | L1: 销售数量 | M1: 销售金额 | N1: 销售毛利 | O1: 销售毛利率
A2: 拼多多-猫人智能家居旗舰店 | B2: 猫人 | C2: 2026-07-12 | D2: 永光 | E2: =D2&"-"&F2 -> 永光-凉感男朋友枕110 | F2: 凉感男朋友枕110 | G2: 猫人男朋友枕凉感蓝 | H2: =VLOOKUP(G2,[1]物料!$A$1:$M$65536,13,0) -> 29.00 | I2: 6.8 | J2: =M2*0.05 -> 212.99 | K2: =(H2+I2)*L2+J2 -> 2504.19 | L2: 64 | M2: 4259.8 | N2: =M2-K2 -> 1755.61 | O2: =N2/M2 -> 0.41213437
A3: 淘宝天猫-猫人居家布艺旗舰 | B3: 猫人 | C3: 2026-07-14 | D3: 眠语 | E3: =D3&"-"&F3 -> 眠语-元抱午睡枕 | F3: 元抱午睡枕 | G3: YBWSZHS04 | H3: =VLOOKUP(G3,[1]物料!$A$1:$M$65536,13,0) -> 18.00 | I3: 6.8 | J3: =M3*0.05 -> 174.975 | K3: =(H3+I3)*L3+J3 -> 1662.975 | L3: 60 | M3: 3499.5 | N3: =M3-K3 -> 1836.525 | O3: =N3/M3 -> 0.5247964
A4: 拼多多-猫人智能家居旗舰店 | B4: 猫人 | C4: 2026-07-10 | D4: 永光 | E4: =D4&"-"&F4 -> 永光-凉感男朋友枕110 | F4: 凉感男朋友枕110 | G4: 猫人男朋友枕凉感蓝 | H4: =VLOOKUP(G4,[1]物料!$A$1:$M$65536,13,0) -> 29.00 | I4: 6.8 | J4: =M4*0.05 -> 195.9835 | K4: =(H4+I4)*L4+J4 -> 2308.1835 | L4: 59 | M4: 3919.67 | N4: =M4-K4 -> 1611.4865 | O4: =N4/M4 -> 0.41112811
A5: 拼多多-猫人智能家居旗舰店 | B5: 猫人 | C5: 2026-07-13 | D5: 永光 | E5: =D5&"-"&F5 -> 永光-凉感男朋友枕110 | F5: 凉感男朋友枕110 | G5: 猫人男朋友枕凉感蓝 | H5: =VLOOKUP(G5,[1]物料!$A$1:$M$65536,13,0) -> 29.00 | I5: 6.8 | J5: =M5*0.05 -> 191.0815 | K5: =(H5+I5)*L5+J5 -> 2267.4815 | L5: 58 | M5: 3821.63 | N5: =M5-K5 -> 1554.1485 | O5: =N5/M5 -> 0.40667163
A6: 拼多多-猫人智能家居旗舰店 | B6: 猫人 | C6: 2026-07-11 | D6: 永光 | E6: =D6&"-"&F6 -> 永光-凉感男朋友枕110 | F6: 凉感男朋友枕110 | G6: 猫人男朋友枕凉感蓝 | H6: =VLOOKUP(G6,[1]物料!$A$1:$M$65536,13,0) -> 29.00 | I6: 6.8 | J6: =M6*0.05 -> 174.215 | K6: =(H6+I6)*L6+J6 -> 2071.615 | L6: 53 | M6: 3484.3 | N6: =M6-K6 -> 1412.685 | O6: =N6/M6 -> 0.40544299
A7: 淘宝天猫-猫人居家布艺旗舰 | B7: 猫人 | C7: 2026-07-13 | D7: 眠语 | E7: =D7&"-"&F7 -> 眠语-元抱午睡枕 | F7: 元抱午睡枕 | G7: YBWSZHS04 | H7: =VLOOKUP(G7,[1]物料!$A$1:$M$65536,13,0) -> 18.00 | I7: 6.8 | J7: =M7*0.05 -> 155.3155 | K7: =(H7+I7)*L7+J7 -> 1469.7155 | L7: 53 | M7: 3106.31 | N7: =M7-K7 -> 1636.5945 | O7: =N7/M7 -> 0.52686129
A8: 淘宝天猫-猫人居家布艺旗舰 | B8: 猫人 | C8: 2026-07-16 | D8: 眠语 | E8: =D8&"-"&F8 -> 眠语-元抱午睡枕 | F8: 元抱午睡枕 | G8: YBWSZHS04 | H8: =VLOOKUP(G8,[1]物料!$A$1:$M$65536,13,0) -> 18.00 | I8: 6.8 | J8: =M8*0.05 -> 146.006 | K8: =(H8+I8)*L8+J8 -> 1386.006 | L8: 50 | M8: 2920.12 | N8: =M8-K8 -> 1534.114 | O8: =N8/M8 -> 0.52535992
A9: 拼多多-猫人智能家居旗舰店 | B9: 猫人 | C9: 2026-07-16 | D9: 永光 | E9: =D9&"-"&F9 -> 永光-凉感男朋友枕110 | F9: 凉感男朋友枕110 | G9: 猫人男朋友枕凉感蓝 | H9: =VLOOKUP(G9,[1]物料!$A$1:$M$65536,13,0) -> 29.00 | I9: 6.8 | J9: =M9*0.05 -> 140.32 | K9: =(H9+I9)*L9+J9 -> 1679.72 | L9: 43 | M9: 2806.4 | N9: =M9-K9 -> 1126.68 | O9: =N9/M9 -> 0.40146807
A10: 淘宝天猫-初医生旗舰店 | B10: 初医生 | C10: 2026-07-13 | D10: 眠语 | E10: =D10&"-"&F10 -> 眠语-海马长条抱枕小号 | F10: 海马长条抱枕小号 | G10: CYS-HMCTBZXHLS | H10: =VLOOKUP(G10,[1]物料!$A$1:$M$65536,13,0) -> 40.00 | I10: 7.2 | J10: =M10*0.05 -> 210.614 | K10: =(H10+I10)*L10+J10 -> 2193.014 | L10: 42 | M10: 4212.28 | N10: =M10-K10 -> 2019.266 | O10: =N10/M10 -> 0.47937601
A11: 淘宝天猫-初医生旗舰店 | B11: 初医生 | C11: 2026-07-12 | D11: 佳雷 | E11: =D11&"-"&F11 -> 佳雷-四叶草褥疮坐垫凝胶小菱格款 | F11: 四叶草褥疮坐垫凝胶小菱格款 | G11: CYS-JLZDRCNJLGC01002 | H11: =VLOOKUP(G11,[1]物料!$A$1:$M$65536,13,0) -> 35.70 | I11: 4 | J11: =M11*0.05 -> 198.7515 | K11: =(H11+I11)*L11+J11 -> 1826.4515 | L11: 41 | M11: 3975.03 | N11: =M11-K11 -> 2148.5785 | O11: =N11/M11 -> 0.54051881
A12: 拼多多-猫人智能家居旗舰店 | B12: 猫人 | C12: 2026-07-15 | D12: 永光 | E12: =D12&"-"&F12 -> 永光-凉感男朋友枕110 | F12: 凉感男朋友枕110 | G12: 猫人男朋友枕凉感蓝 | H12: =VLOOKUP(G12,[1]物料!$A$1:$M$65536,13,0) -> 29.00 | I12: 6.8 | J12: =M12*0.05 -> 129.0335 | K12: =(H12+I12)*L12+J12 -> 1525.2335 | L12: 39 | M12: 2580.67 | N12: =M12-K12 -> 1055.4365 | O12: =N12/M12 -> 0.40897771
A13: 淘宝天猫-猫人居家布艺旗舰 | B13: 猫人 | C13: 2026-07-15 | D13: 眠语 | E13: =D13&"-"&F13 -> 眠语-元抱午睡枕 | F13: 元抱午睡枕 | G13: YBWSZHS04 | H13: =VLOOKUP(G13,[1]物料!$A$1:$M$65536,13,0) -> 18.00 | I13: 6.8 | J13: =M13*0.05 -> 113.6365 | K13: =(H13+I13)*L13+J13 -> 1080.8365 | L13: 39 | M13: 2272.73 | N13: =M13-K13 -> 1191.8935 | O13: =N13/M13 -> 0.52443251
... A5937: 淘宝天猫-初医生旗舰店 | B5937: 初医生 | C5937: 2026-07-10 | D5937: 佐肯 | E5937: =D5937&"-"&F5937 -> 佐肯-洞洞鞋 | F5937: 洞洞鞋 | G5937: 6941918620543 | H5937: =VLOOKUP(G5937,[1]物料!$A$1:$M$65536,13,0) -> 17.50 | I5937: 2.8 | J5937: =M5937*0.05 -> 2.4085 | K5937: =(H5937+I5937)*L5937+J5937 -> 22.7085 | L5937: 1 | M5937: 48.17 | N5937: =M5937-K5937 -> 25.4615 | O5937: =N5937/M5937 -> 0.52857588
